{
  "kind": "collectionType",
  "collectionName": "post_categories",
  "info": {
    "name": "Post Categories",
    "description": ""
  },
  "options": {
    "increments": true,
    "timestamps": true,
    "draftAndPublish": false
  },
  "pluginOptions": {},
  "attributes": {
    "title": {
      "type": "string",
      "required": true
    },
    "slug": {
      "type": "uid",
      "targetField": "title"
    },
    "thumbnail": {
      "model": "file",
      "via": "related",
      "allowedTypes": [
        "images",
        "files",
        "videos"
      ],
      "plugin": "upload",
      "required": false,
      "pluginOptions": {}
    },
    "description": {
      "type": "richtext"
    },
    "posts": {
      "via": "post_categories",
      "collection": "posts",
      "dominant": true
    }
  }
}
